{
  "main": {
    "id": "d118ae019b8c65a6",
    "type": "split",
    "children": [
      {
        "id": "a388804b449998ab",
        "type": "tabs",
        "children": [
          {
            "id": "f982939f82a59dde",
            "type": "leaf",
            "state": {
              "type": "markdown",
              "state": {
                "file": "软件工程/第一章.md",
                "mode": "source",
                "source": false
              }
            }
          },
          {
            "id": "f7dbddadefee2382",
            "type": "leaf",
            "state": {
              "type": "markdown",
              "state": {
                "file": "README.md",
                "mode": "source",
                "source": false
              }
            }
          },
          {
            "id": "60e691f2b856ff36",
            "type": "leaf",
            "state": {
              "type": "markdown",
              "state": {
                "file": "软件工程/第五章.md",
                "mode": "source",
                "source": false
              }
            }
          }
        ],
        "currentTab": 2
      }
    ],
    "direction": "vertical"
  },
  "left": {
    "id": "df3f7ff602855e4c",
    "type": "split",
    "children": [
      {
        "id": "e437d2f1808f402a",
        "type": "tabs",
        "children": [
          {
            "id": "47b650a3bbed1516",
            "type": "leaf",
            "state": {
              "type": "file-explorer",
              "state": {
                "sortOrder": "alphabetical"
              }
            }
          },
          {
            "id": "a842a10a60c9da56",
            "type": "leaf",
            "state": {
              "type": "graph",
              "state": {}
            }
          },
          {
            "id": "7aff4e10b90b1685",
            "type": "leaf",
            "state": {
              "type": "search",
              "state": {
                "query": "",
                "matchingCase": false,
                "explainSearch": false,
                "collapseAll": false,
                "extraContext": false,
                "sortOrder": "alphabetical"
              }
            }
          },
          {
            "id": "dde17eb6b9d7307e",
            "type": "leaf",
            "state": {
              "type": "bookmarks",
              "state": {}
            }
          }
        ]
      }
    ],
    "direction": "horizontal",
    "width": 200
  },
  "right": {
    "id": "65a42c25b4692219",
    "type": "split",
    "children": [
      {
        "id": "17a9cf72ca49b14f",
        "type": "tabs",
        "children": [
          {
            "id": "555c224e651ab836",
            "type": "leaf",
            "state": {
              "type": "backlink",
              "state": {
                "file": "软件工程/第五章.md",
                "collapseAll": false,
                "extraContext": false,
                "sortOrder": "alphabetical",
                "showSearch": false,
                "searchQuery": "",
                "backlinkCollapsed": true,
                "unlinkedCollapsed": true
              }
            }
          },
          {
            "id": "4f7f911ca130e904",
            "type": "leaf",
            "state": {
              "type": "outgoing-link",
              "state": {
                "file": "软件工程/第五章.md",
                "linksCollapsed": false,
                "unlinkedCollapsed": true
              }
            }
          },
          {
            "id": "2d8a5dd4845779b5",
            "type": "leaf",
            "state": {
              "type": "tag",
              "state": {
                "sortOrder": "frequency",
                "useHierarchy": true
              }
            }
          },
          {
            "id": "6f9982f31c19e25a",
            "type": "leaf",
            "state": {
              "type": "outline",
              "state": {
                "file": "软件工程/第五章.md"
              }
            }
          },
          {
            "id": "6085963c53db5058",
            "type": "leaf",
            "state": {
              "type": "advanced-tables-toolbar",
              "state": {}
            }
          }
        ]
      }
    ],
    "direction": "horizontal",
    "width": 249.5,
    "collapsed": true
  },
  "left-ribbon": {
    "hiddenItems": {
      "canvas:新建白板": false,
      "switcher:打开快速切换": false,
      "graph:查看关系图谱": false,
      "daily-notes:打开/创建今天的日记": false,
      "templates:插入模板": false,
      "command-palette:打开命令面板": false,
      "table-editor-obsidian:Advanced Tables Toolbar": false
    }
  },
  "active": "60e691f2b856ff36",
  "lastOpenFiles": [
    "软件工程/第四章.md",
    "软件工程/期末复习.md",
    "软件工程/第三章.md",
    "软件工程/第二章.md",
    "软件工程/第一章.md",
    "README.md",
    "软件工程/第六章.md",
    "数据库作业/数据库作业.md",
    "数据库作业/数据库编程.md",
    "WEB复习题.md",
    "软件工程/第八章.md",
    "软件工程/第十章.md",
    "软件工程/第七章.md",
    "5.md",
    "软件工程/第五章.md",
    "软件工程/第九章.md",
    "软件测试/黑盒测试.md",
    "移动应用开发/UI设计.md",
    "3.md",
    "软件工程/关键路径.svg",
    "软件工程/综合报告.md",
    "未命名.canvas",
    "未命名 1.canvas",
    "计算机接口作业/计算机接口作业.md",
    "4.md",
    "软件测试/web测试.md",
    "软件测试/白盒测试.md",
    "未命名",
    "数据库作业/第 3 章数据表的基本操作.md",
    "移动应用开发",
    "计算机图形学/复习题.md",
    "network/1.log",
    "network/1.aux",
    "network/1.pdf",
    "network/1.tex",
    "network",
    "网络安全/1.tex",
    "网络安全/未命名.tex",
    "网络安全"
  ]
}